Fractocart/__init__.py
Fractocart/main.py
tests/__init__.py
tests/test_main.py
Frac_to_cart_coordinates-1.1.6.dist-info/LICENSE
Frac_to_cart_coordinates-1.1.6.dist-info/METADATA
Frac_to_cart_coordinates-1.1.6.dist-info/WHEEL
Frac_to_cart_coordinates-1.1.6.dist-info/top_level.txt
Frac_to_cart_coordinates-1.1.6.dist-info/RECORD
