Metadata-Version: 2.1
Name: Frac-to-cart-coordinates
Version: 1.1.6
Summary: A lightweight Python package for converting between fractional and Cartesian coordinates, supporting both forward and inverse transformations.
Home-page: https://github.com/n-deveaux/Frac-to-cart-coordinates
Author: Noah Deveaux
Author-email: noah.deveaux@unamur.be
License: UNKNOWN
Platform: UNKNOWN
Classifier: Programming Language :: Python :: 3
Classifier: License :: OSI Approved :: MIT License
Classifier: Operating System :: OS Independent
Requires-Python: >=3.6
License-File: LICENSE
Requires-Dist: numpy
